pyBlendFigures/__init__.py
pyBlendFigures/BlendFiles/BarChart.py
pyBlendFigures/BlendFiles/CreateFrames.py
pyBlendFigures/BlendFiles/ForestPlot.py
pyBlendFigures/BlendFiles/HeatMap.py
pyBlendFigures/BlendFiles/Manhattan.py
pyBlendFigures/BlendFiles/PolyMap.py
pyBlendFigures/BlendFiles/PrismaPlot.py
pyBlendFigures/BlendFiles/QQPlot.py
pyBlendFigures/BlendFiles/Scatter.py
pyBlendFigures/BlendFiles/__init__.py
pyBlendFigures/Constructors/Prisma.py
pyBlendFigures/Constructors/__init__.py
pyBlendFigures/Controller/Base.blend
pyBlendFigures/Controller/BlendFigure.py
pyBlendFigures/Controller/__init__.py
pyBlendFigures/FigureLogic/__init__.py
pyBlendFigures/FigureLogic/heat_map.py
pyBlendFigures/FigureLogic/manhattan_plot.py
pyBlendFigures/FigureLogic/qq_plot.py
pyBlendFigures/Histogram/__init__.py
pyBlendFigures/Histogram/blend_hist.py
pyBlendFigures-0.5.3.dist-info/LICENSE
pyBlendFigures-0.5.3.dist-info/METADATA
pyBlendFigures-0.5.3.dist-info/WHEEL
pyBlendFigures-0.5.3.dist-info/top_level.txt
pyBlendFigures-0.5.3.dist-info/RECORD
