Metadata-Version: 2.1
Name: pyBlendFigures
Version: 0.5.3
Summary: Making modular figures with blender
Home-page: UNKNOWN
Author: Samuel Baker
Author-email: samuelbaker.researcher@gmail.com
Maintainer: Samuel Baker
Maintainer-email: samuelbaker.researcher@gmail.com
License: MIT
Download-URL: https://github.com/sbaker-dev/pyBlendFigures
Platform: UNKNOWN
Classifier: Programming Language :: Python :: 3.7
Classifier: License :: OSI Approved :: MIT License
Requires-Python: >=3.7
Requires-Dist: miscSupports
Requires-Dist: csvObject
Requires-Dist: numpy
Requires-Dist: imageObjects
Requires-Dist: shapeObject
Requires-Dist: blendSupports
Requires-Dist: shapely
Requires-Dist: seaborn
